bunnieddpg/__init__.py
bunnieddpg/actor_net.py
bunnieddpg/agent.py
bunnieddpg/agent_test.py
bunnieddpg/critic_net.py
bunnieddpg/ornstein_uhlenbeck.py
bunnieddpg/ornstein_uhlenbeck_test.py
bunnieddpg/replay_buffer.py
bunnieddpg-0.1.0.dist-info/METADATA
bunnieddpg-0.1.0.dist-info/WHEEL
bunnieddpg-0.1.0.dist-info/top_level.txt
bunnieddpg-0.1.0.dist-info/RECORD
