Metadata-Version: 2.1
Name: bunnieddpg
Version: 0.1.0
Summary: UNKNOWN
Home-page: UNKNOWN
Author: UNKNOWN
Author-email: UNKNOWN
License: UNKNOWN
Platform: UNKNOWN
Requires-Dist: Keras (==2.0.8)
Requires-Dist: numpy (==1.16.2)
Requires-Dist: tensorflow (==1.13.1)
Requires-Dist: h5py (==2.7.1)
Requires-Dist: yapf (==0.17.0)
Requires-Dist: pylint (==1.7.2)
Requires-Dist: pynt (==0.8.2)
